{
    "info": {
        "description": "ISAT",
        "folder": "C:/Repo/D4/final/pic",
        "name": "12.jpg",
        "width": 1322,
        "height": 744,
        "depth": 3,
        "note": ""
    },
    "objects": [
        {
            "category": "player",
            "group": 1,
            "segmentation": [
                [
                    511.0,
                    505.0
                ],
                [
                    509.0,
                    507.0
                ],
                [
                    509.0,
                    523.0
                ],
                [
                    512.0,
                    541.0
                ],
                [
                    512.0,
                    561.0
                ],
                [
                    514.0,
                    566.0
                ],
                [
                    517.0,
                    567.0
                ],
                [
                    522.0,
                    567.0
                ],
                [
                    530.0,
                    566.0
                ],
                [
                    537.0,
                    564.0
                ],
                [
                    539.0,
                    563.0
                ],
                [
                    542.0,
                    560.0
                ],
                [
                    543.0,
                    557.0
                ],
                [
                    544.0,
                    551.0
                ],
                [
                    543.0,
                    541.0
                ],
                [
                    543.0,
                    533.0
                ],
                [
                    544.0,
                    530.0
                ],
                [
                    547.0,
                    524.0
                ],
                [
                    548.0,
                    521.0
                ],
                [
                    548.0,
                    518.0
                ],
                [
                    547.0,
                    515.0
                ],
                [
                    546.0,
                    513.0
                ],
                [
                    544.0,
                    512.0
                ],
                [
                    542.0,
                    512.0
                ],
                [
                    539.0,
                    510.0
                ],
                [
                    534.0,
                    509.0
                ],
                [
                    529.0,
                    506.0
                ],
                [
                    524.0,
                    505.0
                ],
                [
                    519.0,
                    505.0
                ],
                [
                    518.0,
                    504.0
                ],
                [
                    514.0,
                    504.0
                ]
            ],
            "area": 1961.5,
            "layer": 1.0,
            "bbox": [
                508.5,
                503.5,
                548.5,
                567.5
            ],
            "iscrowd": false,
            "note": ""
        },
        {
            "category": "monster",
            "group": 2,
            "segmentation": [
                [
                    564.0,
                    502.0
                ],
                [
                    562.0,
                    504.0
                ],
                [
                    560.0,
                    507.0
                ],
                [
                    555.0,
                    516.0
                ],
                [
                    554.0,
                    519.0
                ],
                [
                    554.0,
                    524.0
                ],
                [
                    556.0,
                    528.0
                ],
                [
                    562.0,
                    538.0
                ],
                [
                    563.0,
                    542.0
                ],
                [
                    564.0,
                    549.0
                ],
                [
                    564.0,
                    564.0
                ],
                [
                    566.0,
                    565.0
                ],
                [
                    570.0,
                    565.0
                ],
                [
                    571.0,
                    564.0
                ],
                [
                    576.0,
                    564.0
                ],
                [
                    578.0,
                    563.0
                ],
                [
                    579.0,
                    554.0
                ],
                [
                    582.0,
                    548.0
                ],
                [
                    583.0,
                    545.0
                ],
                [
                    583.0,
                    535.0
                ],
                [
                    584.0,
                    532.0
                ],
                [
                    588.0,
                    524.0
                ],
                [
                    588.0,
                    520.0
                ],
                [
                    586.0,
                    514.0
                ],
                [
                    584.0,
                    510.0
                ],
                [
                    582.0,
                    508.0
                ],
                [
                    582.0,
                    507.0
                ],
                [
                    581.0,
                    506.0
                ],
                [
                    575.0,
                    503.0
                ],
                [
                    571.0,
                    502.0
                ]
            ],
            "area": 1414.0,
            "layer": 2.0,
            "bbox": [
                553.5,
                501.29289321881345,
                588.5,
                565.5
            ],
            "iscrowd": false,
            "note": ""
        },
        {
            "category": "monster",
            "group": 3,
            "segmentation": [
                [
                    392.0,
                    386.0
                ],
                [
                    389.0,
                    387.0
                ],
                [
                    387.0,
                    388.0
                ],
                [
                    379.0,
                    396.0
                ],
                [
                    377.0,
                    400.0
                ],
                [
                    376.0,
                    406.0
                ],
                [
                    377.0,
                    410.0
                ],
                [
                    379.0,
                    414.0
                ],
                [
                    383.0,
                    419.0
                ],
                [
                    383.0,
                    427.0
                ],
                [
                    381.0,
                    432.0
                ],
                [
                    381.0,
                    437.0
                ],
                [
                    380.0,
                    438.0
                ],
                [
                    380.0,
                    442.0
                ],
                [
                    381.0,
                    446.0
                ],
                [
                    383.0,
                    448.0
                ],
                [
                    391.0,
                    451.0
                ],
                [
                    398.0,
                    451.0
                ],
                [
                    402.0,
                    449.0
                ],
                [
                    405.0,
                    446.0
                ],
                [
                    404.0,
                    427.0
                ],
                [
                    405.0,
                    425.0
                ],
                [
                    409.0,
                    421.0
                ],
                [
                    416.0,
                    420.0
                ],
                [
                    417.0,
                    418.0
                ],
                [
                    417.0,
                    413.0
                ],
                [
                    412.0,
                    404.0
                ],
                [
                    411.0,
                    399.0
                ],
                [
                    409.0,
                    394.0
                ],
                [
                    407.0,
                    390.0
                ],
                [
                    406.0,
                    389.0
                ],
                [
                    402.0,
                    387.0
                ],
                [
                    399.0,
                    386.0
                ]
            ],
            "area": 1785.5,
            "layer": 3.0,
            "bbox": [
                375.50680303808394,
                385.36754446796635,
                417.5,
                451.5
            ],
            "iscrowd": false,
            "note": ""
        },
        {
            "category": "monster",
            "group": 4,
            "segmentation": [
                [
                    790.0,
                    514.0
                ],
                [
                    788.0,
                    515.0
                ],
                [
                    787.0,
                    516.0
                ],
                [
                    786.0,
                    518.0
                ],
                [
                    783.0,
                    527.0
                ],
                [
                    783.0,
                    530.0
                ],
                [
                    784.0,
                    531.0
                ],
                [
                    785.0,
                    536.0
                ],
                [
                    784.0,
                    552.0
                ],
                [
                    784.0,
                    564.0
                ],
                [
                    785.0,
                    566.0
                ],
                [
                    787.0,
                    566.0
                ],
                [
                    788.0,
                    567.0
                ],
                [
                    796.0,
                    567.0
                ],
                [
                    811.0,
                    566.0
                ],
                [
                    815.0,
                    564.0
                ],
                [
                    816.0,
                    561.0
                ],
                [
                    816.0,
                    537.0
                ],
                [
                    814.0,
                    520.0
                ],
                [
                    811.0,
                    516.0
                ],
                [
                    797.0,
                    517.0
                ],
                [
                    793.0,
                    514.0
                ]
            ],
            "area": 1564.5,
            "layer": 4.0,
            "bbox": [
                782.5,
                513.3,
                816.5,
                567.5
            ],
            "iscrowd": false,
            "note": ""
        },
        {
            "category": "monster",
            "group": 5,
            "segmentation": [
                [
                    1038.0,
                    502.0
                ],
                [
                    1030.0,
                    502.0
                ],
                [
                    1024.0,
                    505.0
                ],
                [
                    1016.0,
                    513.0
                ],
                [
                    1013.0,
                    519.0
                ],
                [
                    1012.0,
                    522.0
                ],
                [
                    1012.0,
                    528.0
                ],
                [
                    1014.0,
                    536.0
                ],
                [
                    1014.0,
                    540.0
                ],
                [
                    1013.0,
                    542.0
                ],
                [
                    1010.0,
                    544.0
                ],
                [
                    1009.0,
                    546.0
                ],
                [
                    1009.0,
                    552.0
                ],
                [
                    1010.0,
                    554.0
                ],
                [
                    1013.0,
                    556.0
                ],
                [
                    1014.0,
                    558.0
                ],
                [
                    1014.0,
                    560.0
                ],
                [
                    1015.0,
                    562.0
                ],
                [
                    1018.0,
                    565.0
                ],
                [
                    1032.0,
                    565.0
                ],
                [
                    1035.0,
                    564.0
                ],
                [
                    1041.0,
                    561.0
                ],
                [
                    1045.0,
                    557.0
                ],
                [
                    1047.0,
                    553.0
                ],
                [
                    1048.0,
                    542.0
                ],
                [
                    1049.0,
                    519.0
                ],
                [
                    1048.0,
                    515.0
                ],
                [
                    1046.0,
                    511.0
                ],
                [
                    1041.0,
                    504.0
                ],
                [
                    1040.0,
                    503.0
                ]
            ],
            "area": 2011.5,
            "layer": 5.0,
            "bbox": [
                1008.5,
                501.5,
                1049.4995280791775,
                565.5
            ],
            "iscrowd": false,
            "note": ""
        },
        {
            "category": "monster",
            "group": 6,
            "segmentation": [
                [
                    860.0,
                    388.0
                ],
                [
                    858.0,
                    390.0
                ],
                [
                    855.0,
                    395.0
                ],
                [
                    854.0,
                    399.0
                ],
                [
                    854.0,
                    406.0
                ],
                [
                    855.0,
                    409.0
                ],
                [
                    859.0,
                    413.0
                ],
                [
                    861.0,
                    416.0
                ],
                [
                    863.0,
                    421.0
                ],
                [
                    861.0,
                    426.0
                ],
                [
                    861.0,
                    438.0
                ],
                [
                    863.0,
                    441.0
                ],
                [
                    865.0,
                    443.0
                ],
                [
                    870.0,
                    444.0
                ],
                [
                    876.0,
                    447.0
                ],
                [
                    879.0,
                    451.0
                ],
                [
                    881.0,
                    452.0
                ],
                [
                    884.0,
                    452.0
                ],
                [
                    887.0,
                    449.0
                ],
                [
                    888.0,
                    447.0
                ],
                [
                    888.0,
                    422.0
                ],
                [
                    885.0,
                    415.0
                ],
                [
                    887.0,
                    409.0
                ],
                [
                    887.0,
                    405.0
                ],
                [
                    886.0,
                    404.0
                ],
                [
                    886.0,
                    399.0
                ],
                [
                    884.0,
                    392.0
                ],
                [
                    882.0,
                    388.0
                ],
                [
                    880.0,
                    387.0
                ],
                [
                    872.0,
                    386.0
                ],
                [
                    868.0,
                    386.0
                ]
            ],
            "area": 1663.0,
            "layer": 6.0,
            "bbox": [
                853.5,
                385.5,
                888.5,
                452.5
            ],
            "iscrowd": false,
            "note": ""
        }
    ]
}